venv_update.py
pip_faster.py
pip_faster-1.0rc6.dev4.dist-info/entry_points.txt
pip_faster-1.0rc6.dev4.dist-info/top_level.txt
pip_faster-1.0rc6.dev4.dist-info/METADATA
pip_faster-1.0rc6.dev4.dist-info/metadata.json
pip_faster-1.0rc6.dev4.dist-info/WHEEL
pip_faster-1.0rc6.dev4.dist-info/DESCRIPTION.rst
pip_faster-1.0rc6.dev4.dist-info/RECORD
