Metadata-Version: 2.0
Name: pip-faster
Version: 1.0rc6.dev4
Summary: Quickly and exactly synchronize a virtualenv with a requirements.txt
Home-page: https://github.com/Yelp/pip-faster
Author: Buck Evan
Author-email: buck@yelp.com
License: MIT
Keywords: pip,virtualenv
Platform: a
Platform: l
Platform: l
Classifier: License :: OSI Approved :: MIT License
Classifier: Programming Language :: Python :: 2.6
Classifier: Programming Language :: Python :: 2.7
Classifier: Programming Language :: Python :: 3
Classifier: Programming Language :: Python :: 3.4
Classifier: Programming Language :: Python :: Implementation :: PyPy
Classifier: Topic :: System :: Archiving :: Packaging
Classifier: Operating System :: Unix
Classifier: Intended Audience :: Developers
Classifier: Development Status :: 4 - Beta
Classifier: Environment :: Console
Requires-Dist: virtualenv (>=1.11.5,<2.0)
Requires-Dist: pip (>=1.5.0,<6.0.0)
Requires-Dist: wheel (>0.25.0)
Requires-Dist: setuptools (>=0.8.0)
